[{"id":"bf60c472.30f7d8","type":"tab","label":"RTDS Data","disabled":true,"info":""},{"id":"7210f5d.44e4c0c","type":"mqtt in","z":"bf60c472.30f7d8","name":"telemetry/#","topic":"telemetry/#","qos":"0","datatype":"auto","broker":"73e9a24f.21590c","x":220,"y":220,"wires":[["b16573fe.a0863"]]},{"id":"b16573fe.a0863","type":"function","z":"bf60c472.30f7d8","name":"Topic Filter","func":"try {\n    var inTopic = msg.topic;\n    var thisTopic = \"telemetry/inffeld16/2nd/id2068/littleserver/RJ45\";\n    //node.warn(\"partcnr: \" + inTopic + \" vs \" + thisTopic);\n    if(inTopic.indexOf(thisTopic) >= 0) {\n        //node.warn(\"partcnr: FOUND \" + inTopic + \" vs \" + thisTopic);\n        msg.payload = JSON.parse(msg.payload);\n        return msg;\n    }\n    return null;\n} catch(err) {\n    \n}\nreturn null;","outputs":1,"noerr":0,"initialize":"","finalize":"","x":390,"y":220,"wires":[["4bd7d5fb.dc0ccc"]]},{"id":"4bd7d5fb.dc0ccc","type":"function","z":"bf60c472.30f7d8","name":"Field Filter","func":"try\n{\n    var field = \"bandwidth_Mbps\";\n    if(msg.payload.hasOwnProperty(field))\n    {\n        msg.fieldValue = msg.payload[field];\n        return msg;\n    }\n    return null;\n}\ncatch (err)\n{\n    console.log(\"Field Filter ERROR => \" + err);\n    return null;\n}\n\n\n","outputs":1,"noerr":0,"initialize":"","finalize":"","x":570,"y":220,"wires":[["e7baced5.abcb7","623461b5.f3bdf"]]},{"id":"b7e480eb.574cb","type":"inject","z":"bf60c472.30f7d8","name":"","props":[{"p":"payload"},{"p":"topic","vt":"str"}],"repeat":"","crontab":"","once":true,"onceDelay":0.1,"topic":"","payload":"","payloadType":"date","x":230,"y":160,"wires":[["14f164f0.8997cb"]]},{"id":"14f164f0.8997cb","type":"rtds-create","z":"bf60c472.30f7d8","rtdsName":"Test","dimensionSize":"50","clientFunction":"RRJSIATK_RTDSCreate","x":410,"y":160,"wires":[["9a57491f.c7fdc8"]]},{"id":"9a57491f.c7fdc8","type":"rtds-add-dimension","z":"bf60c472.30f7d8","dimensionName":"Bandwidth","minValue":0,"maxValue":"1200","dataType":1,"clientFunction":"RRJSIATK_RTDSAddDimension","x":610,"y":160,"wires":[[]]},{"id":"e7baced5.abcb7","type":"rtds-get","z":"bf60c472.30f7d8","rtdsName":"Test","onFail":"false","clientFunction":"RRJSIATK_RTDSGet","x":740,"y":220,"wires":[["90676f38.4db22"]]},{"id":"90676f38.4db22","type":"rtds-set-data","z":"bf60c472.30f7d8","dimensionName":"Bandwidth","context":0,"location":"fieldValue","clientFunction":"RRJSIATK_RTDSSetData","x":910,"y":220,"wires":[[]]},{"id":"623461b5.f3bdf","type":"debug","z":"bf60c472.30f7d8","name":"","active":true,"tosidebar":true,"console":false,"tostatus":false,"complete":"fieldValue","targetType":"msg","statusVal":"","statusType":"auto","x":770,"y":280,"wires":[]},{"id":"6c1c6c44.0d85c4","type":"redeploy-message","z":"bf60c472.30f7d8","CNRUpdateBehavior":"1","x":230,"y":400,"wires":[]},{"id":"73e9a24f.21590c","type":"mqtt-broker","name":"","broker":"ragrug-mqtt","port":"1883","clientid":"nodered","usetls":false,"compatmode":false,"keepalive":"60","cleansession":true,"birthTopic":"","birthQos":"0","birthPayload":"","closeTopic":"","closeQos":"0","closePayload":"","willTopic":"","willQos":"0","willPayload":""}]